attotime/__init__.py
attotime/compat.py
attotime/constants.py
attotime/version.py
attotime/objects/__init__.py
attotime/objects/attodatetime.py
attotime/objects/attotime.py
attotime/objects/attotimedelta.py
attotime/objects/tests/__init__.py
attotime/objects/tests/test_attodatetime.py
attotime/objects/tests/test_attotime.py
attotime/objects/tests/test_attotimedelta.py
attotime/tests/__init__.py
attotime/tests/common.py
attotime/tests/compat.py
attotime/tests/test_init.py
attotime/util/__init__.py
attotime/util/strptime.py
attotime/util/tests/__init__.py
attotime/util/tests/test_init.py
attotime/util/tests/test_strptime.py
attotime-0.3.1.dist-info/licenses/LICENSE
attotime-0.3.1.dist-info/METADATA
attotime-0.3.1.dist-info/WHEEL
attotime-0.3.1.dist-info/top_level.txt
attotime-0.3.1.dist-info/RECORD
