Metadata-Version: 2.4
Name: attotime
Version: 0.3.1
Summary: Arbitrary precision datetime library.
Home-page: https://codeberg.org/nielsenb-jf/attotime
Author: Brandon Nielsen
Author-email: nielsenb@jetfuse.net
Project-URL: Changelog, https://codeberg.org/nielsenb-jf/attotime/src/branch/main/CHANGELOG.rst
Project-URL: Documentation, https://attotime.readthedocs.io
Project-URL: Source, https://codeberg.org/nielsenb-jf/attotime
Project-URL: Tracker, https://codeberg.org/nielsenb-jf/attotime/issues
Keywords: datetime decimal
Classifier: Development Status :: 3 - Alpha
Classifier: Intended Audience :: Developers
Classifier: License :: OSI Approved :: BSD License
Classifier: Operating System :: OS Independent
Classifier: Programming Language :: Python
Classifier: Programming Language :: Python :: 2
Classifier: Programming Language :: Python :: 2.7
Classifier: Programming Language :: Python :: 3
Classifier: Programming Language :: Python :: 3.4
Classifier: Programming Language :: Python :: 3.5
Classifier: Programming Language :: Python :: 3.6
Classifier: Programming Language :: Python :: 3.7
Classifier: Programming Language :: Python :: 3.8
Classifier: Programming Language :: Python :: 3.9
Classifier: Topic :: Software Development :: Libraries :: Python Modules
License-File: LICENSE
Provides-Extra: dev
Requires-Dist: black; extra == "dev"
Requires-Dist: coverage; extra == "dev"
Requires-Dist: isort; extra == "dev"
Requires-Dist: pre-commit; extra == "dev"
Requires-Dist: pyenchant; extra == "dev"
Requires-Dist: pylint; extra == "dev"
Dynamic: author
Dynamic: author-email
Dynamic: classifier
Dynamic: description
Dynamic: description-content-type
Dynamic: home-page
Dynamic: keywords
Dynamic: license-file
Dynamic: project-url
Dynamic: provides-extra
Dynamic: summary
